[{"title":"Zedazeni Monastery","categories":"Church / Monastery","pin":"church","coordinates":[{"lat":"41.87115397503697","lon":"44.76549201974217"}],"about":"Zedazeni Monastery - one of the oldest monastery complexes, a monument of architecture, in the Mtskheta-Mtianeti region, northeast of Mtskheta, on the forest-covered Saguramo ridge, at 1170 meters above sea level.","tags":["History","Church","Culture","mountain","Monastery","Forrest","Peak","HistoricalMonument",""],"bestTimeToVisit":"AllSeason","duration":"1 hour","images":["3bb3e798-17928-45a9-ad0d-2d5033569ff8db.jpg","f3652641-2039f-4ac6-bf85-9951aa8ef3977a.jpg","2a059eef-d900d-4e74-8fa9-b33ea46037e999.jpg","b50d2c41-0ea62-4c49-9c72-917123d93b466d.jpg","c573bc63-ed3c3-4403-ab95-4a3a0b9b3cb5d6.jpg"],"location":", Mtskheta "}]