[{"title":"Pshav-Khevsureti National Park","categories":"National Park","pin":"national-parks","coordinates":[{"lat":"42.605713752309896","lon":"45.1186612357214"},{"lat":"42.605713752309896","lon":"45.1186612357214"}],"about":"Pshav-Khevsureti National Park- is situated in the municipality of Dusheti, in one of the most beautiful sides of Georgia, in Pshav-Khevsureti. It has its unique nature, and surroundings, as well as the location, which delights the visitors. In this “corner” of Georgia, there are plenty of sightings and historical or cultural monuments. Pshav-Khevsureti is one of the most known and popular touristic regions of Georgia, with peerless traditions and cuisine. ","tags":["Nature","NationalPark","NationalParks"],"bestTimeToVisit":"AllSeason","duration":"1 day","images":["0b97feff-db696-4b88-b30b-499b8036860c8e.jpg","32e6d484-f716f-4e88-8270-76b10f885aee14.jpg"],"location":", Dusheti "}]